executor_mcp.py
executor_mcp-0.1.0.dist-info/licenses/LICENSE.txt
executor_mcp-0.1.0.dist-info/METADATA
executor_mcp-0.1.0.dist-info/WHEEL
executor_mcp-0.1.0.dist-info/entry_points.txt
executor_mcp-0.1.0.dist-info/top_level.txt
executor_mcp-0.1.0.dist-info/RECORD
