Metadata-Version: 2.4
Name: executor-mcp
Version: 0.1.0
Summary: MCP server for managing interactive CLI binary processes
Author-email: Anthropic <support@anthropic.com>
License: Apache-2.0
Requires-Python: >=3.10
License-File: LICENSE.txt
Requires-Dist: mcp>=1.1.0
Requires-Dist: pydantic>=2.0.0
Provides-Extra: dev
Requires-Dist: pytest>=7.0.0; extra == "dev"
Requires-Dist: pytest-asyncio>=0.21.0; extra == "dev"
Dynamic: license-file
